{
  "game_version": "5.2.2",
  "match_number": 0,
  "characters": {
    "Dwight": 0,
    "Meg": 0,
    "Claudette": 0,
    "Jake": 0,
    "Nea": 0,
    "Laurie": 0,
    "Ace": 0,
    "Bill": 0,
    "Feng": 0,
    "David": 0,
    "Quentin": 0,
    "Tapp": 0,
    "Kate": 0,
    "Adam": 0,
    "Jeff": 0,
    "Jane": 0,
    "Ash": 0,
    "Nancy": 0,
    "Steve": 0,
    "Yui": 0,
    "Zarina": 0,
    "Cheryl": 0,
    "Felix": 0,
    "Elodie": 0,
    "Yun-Jin": 0,
    "Jill": 0,
    "Leon": 0,
    "Jonah Vasquez": 0
  }
}
